{
  "pageNodeId": "n7",
  "pageName": "크루 & 멤버 소개",
  "rootId": "w-01887e",
  "nodes": {
    "w-01887e": {"id":"w-01887e","type":"page","parentId":null,"childrenIds":["w-01887f"],"label":"크루 & 멤버 소개","attributes":{"layout":"website"}},
    "w-01887f": {"id":"w-01887f","type":"body","parentId":"w-01887e","childrenIds":["w-018880"]},
    "w-018880": {"id":"w-018880","type":"column","parentId":"w-01887f","childrenIds":["w-018881","w-018884","w-018895","w-0188a8"],"layout":{"gap":32}},
    "w-018881": {"id":"w-018881","type":"column","parentId":"w-018880","childrenIds":["w-018882","w-018883"],"layout":{"gap":8}},
    "w-018882": {"id":"w-018882","type":"text","parentId":"w-018881","childrenIds":[],"label":"크루 & 멤버 소개","size":"md"},
    "w-018883": {"id":"w-018883","type":"text","parentId":"w-018881","childrenIds":[],"label":"고래상사 크루의 세계관과 구성원을 한눈에 파악하세요","size":"sm"},
    "w-018884": {"id":"w-018884","type":"box","parentId":"w-018880","childrenIds":["w-018885"]},
    "w-018885": {"id":"w-018885","type":"column","parentId":"w-018884","childrenIds":["w-018886","w-018887","w-018888"],"layout":{"gap":12}},
    "w-018886": {"id":"w-018886","type":"text","parentId":"w-018885","childrenIds":[],"label":"고래상사에 오신 것을 환영합니다","size":"lg"},
    "w-018887": {"id":"w-018887","type":"text","parentId":"w-018885","childrenIds":[],"label":"고래상사는 회사 역할극을 기반으로 한 크리에이터 크루입니다. 각자의 직책과 캐릭터로 살아가는 이 세계관 속에서 진짜 같은 가짜 회사 생활을 함께 즐겨보세요."},
    "w-018888": {"id":"w-018888","type":"row","parentId":"w-018885","childrenIds":["w-018889","w-01888d","w-018891"],"layout":{"gap":16}},
    "w-018889": {"id":"w-018889","type":"box","parentId":"w-018888","childrenIds":["w-01888a","w-01888b","w-01888c"],"attributes":{"outlined":""}},
    "w-01888a": {"id":"w-01888a","type":"text","parentId":"w-018889","childrenIds":[],"label":"크루 미션","size":"md"},
    "w-01888b": {"id":"w-01888b","type":"text","parentId":"w-018889","childrenIds":[],"label":"진지하게 즐기는 가상 직장 생활"},
    "w-01888c": {"id":"w-01888c","type":"text","parentId":"w-018889","childrenIds":[],"label":"역할과 세계관을 유지하며 콘텐츠를 만들어갑니다.","size":"sm"},
    "w-01888d": {"id":"w-01888d","type":"box","parentId":"w-018888","childrenIds":["w-01888e","w-01888f","w-018890"],"attributes":{"outlined":""}},
    "w-01888e": {"id":"w-01888e","type":"text","parentId":"w-01888d","childrenIds":[],"label":"크루 가치","size":"md"},
    "w-01888f": {"id":"w-01888f","type":"text","parentId":"w-01888d","childrenIds":[],"label":"몰입, 유머, 연대"},
    "w-018890": {"id":"w-018890","type":"text","parentId":"w-01888d","childrenIds":[],"label":"서로의 캐릭터를 존중하고 함께 세계관을 넓혀갑니다.","size":"sm"},
    "w-018891": {"id":"w-018891","type":"box","parentId":"w-018888","childrenIds":["w-018892","w-018893","w-018894"],"attributes":{"outlined":""}},
    "w-018892": {"id":"w-018892","type":"text","parentId":"w-018891","childrenIds":[],"label":"크루 규모","size":"md"},
    "w-018893": {"id":"w-018893","type":"text","parentId":"w-018891","childrenIds":[],"label":"총 12명의 크루원"},
    "w-018894": {"id":"w-018894","type":"text","parentId":"w-018891","childrenIds":[],"label":"다양한 부서와 직책으로 구성된 멀티 크리에이터 그룹입니다.","size":"sm"},
    "w-018895": {"id":"w-018895","type":"column","parentId":"w-018880","childrenIds":["w-018896","w-018897"],"layout":{"gap":16}},
    "w-018896": {"id":"w-018896","type":"text","parentId":"w-018895","childrenIds":[],"label":"멤버 미리보기","size":"md"},
    "w-018897": {"id":"w-018897","type":"row","parentId":"w-018895","childrenIds":["w-018898","w-01889c","w-0188a0","w-0188a4"],"layout":{"gap":16}},
    "w-018898": {"id":"w-018898","type":"box","parentId":"w-018897","childrenIds":["w-018899","w-01889a","w-01889b"]},
    "w-018899": {"id":"w-018899","type":"image","parentId":"w-018898","childrenIds":[],"label":"멤버 프로필","layout":{"height":120}},
    "w-01889a": {"id":"w-01889a","type":"text","parentId":"w-018898","childrenIds":[],"label":"김대리"},
    "w-01889b": {"id":"w-01889b","type":"text","parentId":"w-018898","childrenIds":[],"label":"영업부 / 막내 대리","size":"sm"},
    "w-01889c": {"id":"w-01889c","type":"box","parentId":"w-018897","childrenIds":["w-01889d","w-01889e","w-01889f"]},
    "w-01889d": {"id":"w-01889d","type":"image","parentId":"w-01889c","childrenIds":[],"label":"멤버 프로필","layout":{"height":120}},
    "w-01889e": {"id":"w-01889e","type":"text","parentId":"w-01889c","childrenIds":[],"label":"이과장"},
    "w-01889f": {"id":"w-01889f","type":"text","parentId":"w-01889c","childrenIds":[],"label":"기획부 / 중간 관리자","size":"sm"},
    "w-0188a0": {"id":"w-0188a0","type":"box","parentId":"w-018897","childrenIds":["w-0188a1","w-0188a2","w-0188a3"]},
    "w-0188a1": {"id":"w-0188a1","type":"image","parentId":"w-0188a0","childrenIds":[],"label":"멤버 프로필","layout":{"height":120}},
    "w-0188a2": {"id":"w-0188a2","type":"text","parentId":"w-0188a0","childrenIds":[],"label":"박팀장"},
    "w-0188a3": {"id":"w-0188a3","type":"text","parentId":"w-0188a0","childrenIds":[],"label":"개발부 / 팀장","size":"sm"},
    "w-0188a4": {"id":"w-0188a4","type":"box","parentId":"w-018897","childrenIds":["w-0188a5","w-0188a6","w-0188a7"]},
    "w-0188a5": {"id":"w-0188a5","type":"image","parentId":"w-0188a4","childrenIds":[],"label":"멤버 프로필","layout":{"height":120}},
    "w-0188a6": {"id":"w-0188a6","type":"text","parentId":"w-0188a4","childrenIds":[],"label":"최부장"},
    "w-0188a7": {"id":"w-0188a7","type":"text","parentId":"w-0188a4","childrenIds":[],"label":"총무부 / 부장","size":"sm"},
    "w-0188a8": {"id":"w-0188a8","type":"row","parentId":"w-018880","childrenIds":["w-0188a9","w-0188ae"],"layout":{"gap":16}},
    "w-0188a9": {"id":"w-0188a9","type":"box","parentId":"w-0188a8","childrenIds":["w-0188aa"],"action":{"type":"navigate","targetPageNodeId":"n9"},"attributes":{"outlined":""}},
    "w-0188aa": {"id":"w-0188aa","type":"column","parentId":"w-0188a9","childrenIds":["w-0188ab","w-0188ac","w-0188ad"],"layout":{"gap":8}},
    "w-0188ab": {"id":"w-0188ab","type":"text","parentId":"w-0188aa","childrenIds":[],"label":"전체 멤버 목록","size":"md"},
    "w-0188ac": {"id":"w-0188ac","type":"text","parentId":"w-0188aa","childrenIds":[],"label":"모든 크루원의 프로필과 캐릭터 설정을 확인하세요.","size":"sm"},
    "w-0188ad": {"id":"w-0188ad","type":"button","parentId":"w-0188aa","childrenIds":[],"label":"멤버 목록 보기","variant":"primary","action":{"type":"navigate","targetPageNodeId":"n9"}},
    "w-0188ae": {"id":"w-0188ae","type":"box","parentId":"w-0188a8","childrenIds":["w-0188af"],"action":{"type":"navigate","targetPageNodeId":"n8"},"attributes":{"outlined":""}},
    "w-0188af": {"id":"w-0188af","type":"column","parentId":"w-0188ae","childrenIds":["w-0188b0","w-0188b1","w-0188b2"],"layout":{"gap":8}},
    "w-0188b0": {"id":"w-0188b0","type":"text","parentId":"w-0188af","childrenIds":[],"label":"크루 소개 자세히 보기","size":"md"},
    "w-0188b1": {"id":"w-0188b1","type":"text","parentId":"w-0188af","childrenIds":[],"label":"고래상사의 세계관, 설립 배경, 조직 구조를 더 깊이 탐색하세요.","size":"sm"},
    "w-0188b2": {"id":"w-0188b2","type":"button","parentId":"w-0188af","childrenIds":[],"label":"크루 소개 보기","action":{"type":"navigate","targetPageNodeId":"n8"}}
  }
}
